whatalang/__init__.py
whatalang/cli.py
whatalang/grammar.py
whatalang/lexer.py
whatalang/parser.py
whatalang/reactive.py
whatalang/state.py
whatalang-1.0.0.dist-info/METADATA
whatalang-1.0.0.dist-info/WHEEL
whatalang-1.0.0.dist-info/entry_points.txt
whatalang-1.0.0.dist-info/top_level.txt
whatalang-1.0.0.dist-info/RECORD
