Metadata-Version: 2.4
Name: whatalang
Version: 1.0.0
Summary: A reactive programming language
Author-email: Whatalang Team <team@whatalang.dev>
License: MIT
Project-URL: Homepage, https://github.com/whatalang/whatalang
Project-URL: Repository, https://github.com/whatalang/whatalang
Project-URL: Documentation, https://whatalang.dev
Project-URL: Issues, https://github.com/whatalang/whatalang/issues
Classifier: Development Status :: 4 - Beta
Classifier: Intended Audience :: Developers
Classifier: License :: OSI Approved :: MIT License
Classifier: Programming Language :: Python :: 3
Classifier: Programming Language :: Python :: 3.8
Classifier: Programming Language :: Python :: 3.9
Classifier: Programming Language :: Python :: 3.10
Classifier: Programming Language :: Python :: 3.11
Classifier: Programming Language :: Python :: 3.12
Classifier: Programming Language :: Python :: 3.13
Classifier: Topic :: Software Development :: Interpreters
Classifier: Topic :: Software Development :: Libraries :: Python Modules
Requires-Python: >=3.8
Provides-Extra: dev
Requires-Dist: pytest>=7.0.0; extra == "dev"
Requires-Dist: pytest-cov>=4.0.0; extra == "dev"
